{
	"name": "blood_back",
	"plugin-id": "Sprite",
	"sid": 352928786890110,
	"isGlobal": false,
	"instanceVariables": [],
	"behaviorTypes": [
		{
			"behaviorId": "Anchor",
			"name": "Якорь",
			"sid": 783907709367714
		}
	],
	"effectTypes": [],
	"animations": {
		"items": [
			{
				"frames": [
					{
						"width": 44,
						"height": 64,
						"originX": 0.7323667711598746,
						"originY": 0.9507472826086956,
						"originalSource": "",
						"exportFormat": "png",
						"exportQuality": 0.8,
						"imageSpriteId": 7685950,
						"collisionPoly": {
							"points": [
								0.1982758620689655,
								0.296875,
								0.7323667711598746,
								0,
								0.7876175548589341,
								0.500679347826087,
								0.8981191222570536,
								0.9507472826086956,
								0.7323667711598746,
								1,
								0.0877742946708464,
								0.9507472826086956
							]
						},
						"useCollisionPoly": true,
						"duration": 1
					}
				],
				"sid": 710135218098895,
				"name": "Animation 1",
				"isLooping": false,
				"isPingPong": false,
				"repeatCount": 1,
				"repeatTo": 0,
				"speed": 5
			}
		],
		"subfolders": []
	}
}