{
	"name": "Blood",
	"plugin-id": "Sprite",
	"sid": 352928786890110,
	"isGlobal": false,
	"instanceVariables": [
		{
			"name": "blood",
			"type": "number",
			"desc": "",
			"sid": 378796123420345
		}
	],
	"behaviorTypes": [
		{
			"behaviorId": "Anchor",
			"name": "Якорь",
			"sid": 610297260163764
		}
	],
	"effectTypes": [],
	"animations": {
		"items": [
			{
				"frames": [
					{
						"width": 44,
						"height": 64,
						"originX": 0.5,
						"originY": 0.5,
						"originalSource": "",
						"exportFormat": "png",
						"exportQuality": 0.8,
						"imageSpriteId": 3172509,
						"useCollisionPoly": true,
						"duration": 1
					},
					{
						"width": 44,
						"height": 64,
						"originX": 0.5,
						"originY": 0.5,
						"originalSource": "",
						"exportFormat": "png",
						"exportQuality": 0.8,
						"imageSpriteId": 3580734,
						"useCollisionPoly": true,
						"duration": 1
					},
					{
						"width": 44,
						"height": 64,
						"originX": 0.5,
						"originY": 0.5,
						"originalSource": "",
						"exportFormat": "png",
						"exportQuality": 0.8,
						"imageSpriteId": 1797501,
						"useCollisionPoly": true,
						"duration": 1
					},
					{
						"width": 44,
						"height": 64,
						"originX": 0.5,
						"originY": 0.5,
						"originalSource": "",
						"exportFormat": "png",
						"exportQuality": 0.8,
						"imageSpriteId": 6661691,
						"useCollisionPoly": true,
						"duration": 1
					},
					{
						"width": 44,
						"height": 64,
						"originX": 0.5,
						"originY": 0.5,
						"originalSource": "",
						"exportFormat": "png",
						"exportQuality": 0.8,
						"imageSpriteId": 1930749,
						"useCollisionPoly": true,
						"duration": 1
					},
					{
						"width": 44,
						"height": 64,
						"originX": 0.5,
						"originY": 0.5,
						"originalSource": "",
						"exportFormat": "png",
						"exportQuality": 0.8,
						"imageSpriteId": 1122273,
						"useCollisionPoly": true,
						"duration": 1
					},
					{
						"width": 44,
						"height": 64,
						"originX": 0.5,
						"originY": 0.5,
						"originalSource": "",
						"exportFormat": "png",
						"exportQuality": 0.8,
						"imageSpriteId": 7630486,
						"useCollisionPoly": true,
						"duration": 1
					},
					{
						"width": 44,
						"height": 64,
						"originX": 0.5,
						"originY": 0.5,
						"originalSource": "",
						"exportFormat": "png",
						"exportQuality": 0.8,
						"imageSpriteId": 1534341,
						"useCollisionPoly": true,
						"duration": 1
					},
					{
						"width": 44,
						"height": 64,
						"originX": 0.5,
						"originY": 0.5,
						"originalSource": "",
						"exportFormat": "png",
						"exportQuality": 0.8,
						"imageSpriteId": 7786609,
						"useCollisionPoly": true,
						"duration": 1
					},
					{
						"width": 44,
						"height": 64,
						"originX": 0.5,
						"originY": 0.5,
						"originalSource": "",
						"exportFormat": "png",
						"exportQuality": 0.8,
						"imageSpriteId": 5632342,
						"useCollisionPoly": true,
						"duration": 1
					},
					{
						"width": 44,
						"height": 64,
						"originX": 0.5,
						"originY": 0.5,
						"originalSource": "",
						"exportFormat": "png",
						"exportQuality": 0.8,
						"imageSpriteId": 6146480,
						"useCollisionPoly": true,
						"duration": 1
					},
					{
						"width": 44,
						"height": 64,
						"originX": 0.5,
						"originY": 0.5,
						"originalSource": "",
						"exportFormat": "png",
						"exportQuality": 0.8,
						"imageSpriteId": 8420637,
						"useCollisionPoly": true,
						"duration": 1
					},
					{
						"width": 44,
						"height": 64,
						"originX": 0.5,
						"originY": 0.5,
						"originalSource": "",
						"exportFormat": "png",
						"exportQuality": 0.8,
						"imageSpriteId": 3262478,
						"useCollisionPoly": true,
						"duration": 1
					},
					{
						"width": 44,
						"height": 64,
						"originX": 0.5,
						"originY": 0.5,
						"originalSource": "",
						"exportFormat": "png",
						"exportQuality": 0.8,
						"imageSpriteId": 3071706,
						"useCollisionPoly": true,
						"duration": 1
					},
					{
						"width": 44,
						"height": 64,
						"originX": 0.5,
						"originY": 0.5,
						"originalSource": "",
						"exportFormat": "png",
						"exportQuality": 0.8,
						"imageSpriteId": 4988040,
						"useCollisionPoly": true,
						"duration": 1
					},
					{
						"width": 44,
						"height": 64,
						"originX": 0.5,
						"originY": 0.5,
						"originalSource": "",
						"exportFormat": "png",
						"exportQuality": 0.8,
						"imageSpriteId": 587473,
						"useCollisionPoly": true,
						"duration": 1
					},
					{
						"width": 44,
						"height": 64,
						"originX": 0.5,
						"originY": 0.5,
						"originalSource": "",
						"exportFormat": "png",
						"exportQuality": 0.8,
						"imageSpriteId": 7824812,
						"useCollisionPoly": true,
						"duration": 1
					},
					{
						"width": 44,
						"height": 64,
						"originX": 0.5,
						"originY": 0.5,
						"originalSource": "",
						"exportFormat": "png",
						"exportQuality": 0.8,
						"imageSpriteId": 8642708,
						"useCollisionPoly": true,
						"duration": 1
					},
					{
						"width": 44,
						"height": 64,
						"originX": 0.5,
						"originY": 0.5,
						"originalSource": "",
						"exportFormat": "png",
						"exportQuality": 0.8,
						"imageSpriteId": 5135399,
						"useCollisionPoly": true,
						"duration": 1
					},
					{
						"width": 44,
						"height": 64,
						"originX": 0.5,
						"originY": 0.5,
						"originalSource": "",
						"exportFormat": "png",
						"exportQuality": 0.8,
						"imageSpriteId": 7320508,
						"useCollisionPoly": true,
						"duration": 1
					},
					{
						"width": 44,
						"height": 64,
						"originX": 0.5,
						"originY": 0.5,
						"originalSource": "",
						"exportFormat": "png",
						"exportQuality": 0.8,
						"imageSpriteId": 1373685,
						"useCollisionPoly": true,
						"duration": 1
					}
				],
				"sid": 710135218098895,
				"name": "Animation 1",
				"isLooping": false,
				"isPingPong": false,
				"repeatCount": 1,
				"repeatTo": 0,
				"speed": 0
			}
		],
		"subfolders": []
	}
}